runqdm/__init__.py
runqdm/running_man_frame/ascii-art (1).txt
runqdm/running_man_frame/ascii-art (10).txt
runqdm/running_man_frame/ascii-art (2).txt
runqdm/running_man_frame/ascii-art (3).txt
runqdm/running_man_frame/ascii-art (4).txt
runqdm/running_man_frame/ascii-art (5).txt
runqdm/running_man_frame/ascii-art (6).txt
runqdm/running_man_frame/ascii-art (7).txt
runqdm/running_man_frame/ascii-art (8).txt
runqdm/running_man_frame/ascii-art (9).txt
runqdm/running_man_frame/ascii-art.txt
runqdm-1.0.1.dist-info/LICENSE
runqdm-1.0.1.dist-info/METADATA
runqdm-1.0.1.dist-info/WHEEL
runqdm-1.0.1.dist-info/top_level.txt
runqdm-1.0.1.dist-info/RECORD
