Metadata-Version: 2.2
Name: runqdm
Version: 1.0.1
Summary: A running progress bar package with animation
Home-page: https://github.com/hangilzzang/runqdm.git
Author: hangilzzang
Author-email: gkrwhddlwjqrl@gmail.com
Classifier: Programming Language :: Python :: 3
Classifier: License :: OSI Approved :: MIT License
Classifier: Operating System :: OS Independent
Requires-Python: >=3.6
License-File: LICENSE
Requires-Dist: setuptools
Requires-Dist: colorama
Dynamic: author
Dynamic: author-email
Dynamic: classifier
Dynamic: description
Dynamic: description-content-type
Dynamic: home-page
Dynamic: requires-dist
Dynamic: requires-python
Dynamic: summary
